CHANGES.rst
MANIFEST.in
Makefile
Makefile.release
README.rst
setup.py
version.txt
src/metapensiero.sqlalchemy.asyncio.egg-info/PKG-INFO
src/metapensiero.sqlalchemy.asyncio.egg-info/SOURCES.txt
src/metapensiero.sqlalchemy.asyncio.egg-info/dependency_links.txt
src/metapensiero.sqlalchemy.asyncio.egg-info/namespace_packages.txt
src/metapensiero.sqlalchemy.asyncio.egg-info/requires.txt
src/metapensiero.sqlalchemy.asyncio.egg-info/top_level.txt
src/metapensiero/sqlalchemy/asyncio/__init__.py
tests/_test_connect_35.py
tests/conftest.py
tests/test_connect.py