Metadata-Version: 2.1
Name: metapensiero.sqlalchemy.asyncio
Version: 1.0
Summary: Asyncio middleware for SQLAlchemy
Home-page: https://gitlab.com/metapensiero/metapensiero.sqlalchemy.asyncio
Author: Alberto Berti
Author-email: azazel@metapensiero.it
Maintainer: Lele Gaifax
Maintainer-email: lele@metapensiero.it
License: GPLv3+
Keywords: asyncio sqlalchemy
Platform: UNKNOWN
Classifier: Programming Language :: Python
Classifier: Programming Language :: Python :: 3
Classifier: Programming Language :: Python :: 3.4
Classifier: Programming Language :: Python :: 3.5
Classifier: Programming Language :: Python :: 3.6
Classifier: Programming Language :: Python :: 3.7
Classifier: Intended Audience :: Developers
Classifier: License :: OSI Approved :: GNU General Public License v3 or later (GPLv3+)
Classifier: Topic :: Database
Provides-Extra: dev
